seamlessvalidation/__init__.py
seamlessvalidation/monitoring/__init__.py
seamlessvalidation/monitoring/data_drift.py
seamlessvalidation/monitoring/model_drift.py
seamlessvalidation/monitoring/performance_monitoring.py
seamlessvalidation/utils/__init__.py
seamlessvalidation/utils/data_utils.py
seamlessvalidation/validation/__init__.py
seamlessvalidation/validation/allin1_validation.py
seamlessvalidation/validation/clustering_validation.py
seamlessvalidation/validation/keymetrics.py
seamlessvalidation/validation/main copy.py
seamlessvalidation/validation/main.py
seamlessvalidation-0.22.dist-info/LICENSE
seamlessvalidation-0.22.dist-info/METADATA
seamlessvalidation-0.22.dist-info/WHEEL
seamlessvalidation-0.22.dist-info/top_level.txt
seamlessvalidation-0.22.dist-info/RECORD
