Metadata-Version: 2.1
Name: seamlessvalidation
Version: 0.22
Summary: A package for easy validation and post deployment monitoring of common linear and non linear ML models and clustering model
Author: ZhuZheng(Iverson) ZHOU
Author-email: zzho044@aucklanduni.ac.nz
Keywords: machine learning validation monitoring
License-File: LICENSE
Requires-Dist: scikit-learn
Requires-Dist: pandas
Requires-Dist: numpy
Requires-Dist: matplotlib
Requires-Dist: pickle
Requires-Dist: scipy
